netools/__init__.py
netools/hello.py
netools/streaming.py
netools-0.0.2.dist-info/LICENSE
netools-0.0.2.dist-info/METADATA
netools-0.0.2.dist-info/WHEEL
netools-0.0.2.dist-info/top_level.txt
netools-0.0.2.dist-info/RECORD
