Metadata-Version: 2.1
Name: netools
Version: 0.0.2
Summary: Prints Hello
Author: Nelson Wang
Author-email: <wangnelson2@gmail.com>
License: UNKNOWN
Keywords: python,utilities
Platform: UNKNOWN
Classifier: Development Status :: 1 - Planning
Classifier: Intended Audience :: Developers
Classifier: Programming Language :: Python :: 3
Classifier: Operating System :: Unix
Classifier: Operating System :: MacOS :: MacOS X
Classifier: Operating System :: Microsoft :: Windows
License-File: LICENSE
